{
  "swagger": "2.0",
  "info": {
    "title": "argus-case-eapi",
    "version": "1.0.0"
  },
  "schemes": [
    "https"
  ],
  "externalDocs": {
    "url": "http://",
    "description": "# Title\nExperience Case API\n\n# API Overview\n\nDescription: Experience Case API allows to \n-  Create and Retrieve Case Notes\n-  Create and Retrieve Case Tasks\n-  Retrieve and Update Case Authorizations\n-  Retrieve Case Documents.\n-  Retrieve Cases Summary by Client Id\n\n# Security\n** Client Id enforcement ** -> client_id and client_secret should be passed as part of headers\n\n** X-Forwarded-For ** -> The originating IP address of a client hould be passes as part of headers \"X-Forwarded-For\".\n\n# Resources\n\n      GET   /v1/healthcheck\n      GET   /v1/cases\n      GET   /v1/cases/{caseId}/notes\n      POST  /v1/cases/{caseId}/notes\n      GET   /v1/cases/{caseId}/tasks\n      POST  /v1/cases/{caseId}/tasks\n      GET   /v1/cases/{caseId}/authorizations\n      PATCH /v1/cases/{caseId}/authorizations/{authorizationId}\n      GET   /v1/cases/{caseId}/documents\n# Notes\n\n** Correlation Id enforcement ** -> X-Correlation-ID should be passed as part of headers\n\nAll GET Endpoints support Pagination, by passing below query params\n\n```sh\noffset:\n  description: Skip over a number of elements by specifying an offset value for the query\n  type: integer\n  required: false\n  example: 20\n  default: 0\nlimit:\n  description: Limit the number of elements on the response\n  type: integer\n  required: false\n  example: 80\n  default: 10\n```      \n\n# Status Codes\n\n- All GET endpoints return below HTTP Status Codes:\n\n```sh\n200 - Success\n401 - Access Denied\n403 - Forbidden\n404 - Not Found\n405 - Method not allowed\n500 - Internal Server Error\n```\n\n- All PATCH endpoints return below HTTP Status Codes:\n```sh\n200 - Success\n400 - Bad Request\n401 - Access Denied\n403 - Forbidden\n405 - Method not allowed\n500 - Internal Server Error\n```\n- All POST endpoints return below HTTP Status Codes:\n```sh\n202 - Accepted\n400 - Bad Request\n401 - Access Denied\n403 - Forbidden\n405 - Method not allowed\n500 - Internal Server Error\n```\n\n# Examples\n\n    GET   /v1/healthcheck\n    Description: Get Status of the API.\n\n```sh\n    Response:\n{\n  \"message\" : \"Success\"\n}\n```\n\n    GET   /v1/cases/{caseId}/notes\n    Description: Get ALL Notes for a Case\n\n```sh\n    Request:\n      - uri params: \n        - caseId: 1234\n      - query params:\n        - requestedDateTime:\n          - required: false\n          - type: dateTime\n          - format: rfc3339\n        - offset:\n          - description: Skip over a number of elements by specifying an offset value for the query\n          - required: false\n          - type: integer\n        - limit:\n          - description: Limit the number of elements on the response\n          - required: false\n          - type: integer\n```\n\n```sh\n    Response:\n[\n    {\n        \"caseId\": 3974,\n        \"noteId\": 2941,\n        \"type\": \"Note\",\n        \"noteType\": {\n            \"type\": \"NoteType\",\n            \"id\": 11903,\n            \"key\": \"030:carrier\",\n            \"description\": \"Carrier Note\"\n        },\n        \"note\": \"Air lift needed to John Smith immediately in relation to approved auth\",\n        \"noteAuthor\": \"One Team Health\",\n        \"noteCreatedDate\": \"2020-11-18T04:00:00\",\n        \"direction\": \"Inbound\",\n        \"code\": \"Email\",\n        \"caller\": \"\",\n        \"callee\": \"\",\n        \"createdDateTime\": \"2020-11-18T13:32:58.470Z\",\n        \"modifiedDateTime\": \"2020-11-18T13:32:58.470Z\"\n    },\n    {\n        \"caseId\": 3974,\n        \"noteId\": 2943,\n        \"type\": \"Note\",\n        \"noteType\": {\n            \"type\": \"NoteType\",\n            \"id\": 11903,\n            \"key\": \"030:carrier\",\n            \"description\": \"Carrier Note\"\n        },\n        \"note\": \"Medical notes Fallon Serv\",\n        \"noteAuthor\": \"One Team Health\",\n        \"noteCreatedDate\": \"2020-11-18T04:00:00\",\n        \"direction\": \"Inbound\",\n        \"code\": \"Email\",\n        \"caller\": \"\",\n        \"callee\": \"\",\n        \"createdDateTime\": \"2020-11-18T16:57:39.397Z\",\n        \"modifiedDateTime\": \"2020-11-18T16:57:39.397Z\"\n    },\n    {\n        \"caseId\": 3974,\n        \"noteId\": 2948,\n        \"type\": \"Note\",\n        \"noteType\": {\n            \"type\": \"NoteType\",\n            \"id\": 11903,\n            \"key\": \"030:carrier\",\n            \"description\": \"Carrier Note\"\n        },\n        \"note\": \"Medical notes Fallon Serv\",\n        \"noteAuthor\": \"One Team Health\",\n        \"noteCreatedDate\": \"2020-11-18T04:00:00\",\n        \"direction\": \"Inbound\",\n        \"code\": \"Email\",\n        \"caller\": \"\",\n        \"callee\": \"\",\n        \"createdDateTime\": \"2020-11-18T19:36:28.733Z\",\n        \"modifiedDateTime\": \"2020-11-18T19:36:28.733Z\"\n    }\n]\n```\n    POST   /v1/cases/{caseId}/notes\n    Description: Create a Note to a Case\n```sh\n    Request:\n      - uri params: \n        - caseId: 1234\n      - body:\n        - {\n            \"uuid\": \"a25f5974-e7df-43be-b048-23f55e29c971\",\n            \"type\": \"Note\",\n            \"note\": \"Lorem ipsum\"\n          }  \n```\n```sh\n    Response:\n```\n    GET   /v1/cases/{caseId}/tasks\n    Description: Get ALL tasks for a Case\n\n```sh\n    Request:\n      - uri params: \n        - caseId: 1234\n      - query params:\n        - requestedDateTime:\n          - required: false\n          - type: dateTime\n          - format: rfc3339\n        - offset:\n          - description: Skip over a number of elements by specifying an offset value for the query\n          - required: false\n          - type: integer\n        - limit:\n          - description: Limit the number of elements on the response\n          - required: false\n          - type: integer\n```\n```sh\n    Response:\n[\n    {\n         \"caseId\":3261,\n         \"taskId\":5883,\n         \"taskType\":{\n            \"type\":\"TaskType\",\n            \"id\":2050,\n            \"key\":\"TSK:2050\",\n            \"description\":\"Assign Case\"\n         },\n         \"startDate\":\"2020-07-02T03:00:00\",\n         \"completedDate\":\"2020-07-02T03:00:00\",\n         \"dueDate\":\"2020-07-03T03:00:00\",\n         \"taskStatus\":{\n            \"type\":\"TaskStatus\",\n            \"id\":426,\n            \"key\":\"048:T-Completed\",\n            \"description\":\"Completed\"\n         },\n         \"createdDateTime\":\"2020-07-02T12:15:01.473Z\",\n         \"modifiedDateTime\":\"2020-07-02T12:15:01.473Z\",\n         \"priority\" : \"004:Medium\"\n      }\n]\n```\n    POST   /v1/cases/{caseId}/tasks\n    Description: Create a task to a Case\n```sh\n    Request:\n      - uri params: \n        - caseId: 1234\n      - body:\n        - {\n            \"uuid\": \"a25f5974-e7df-43be-b048-23f55e29c971\",\n            \"type\": \"NNNNNNN\",\n            \"priority\": \"High\",\n            \"startDate\": \"2020-06-01\"\n          }  \n```\n```sh\n    Response:\n```\n    GET   /v1/cases/{caseId}/authorizations\n    Description: Get ALL Authorizations for a Case\n\n```sh\n    Request:\n      - uri params: \n        - caseId: 1234\n      - query params:\n        - requestedDateTime:\n          - required: false\n          - type: dateTime\n          - format: rfc3339\n        - offset:\n          - description: Skip over a number of elements by specifying an offset value for the query\n          - required: false\n          - type: integer\n        - limit:\n          - description: Limit the number of elements on the response\n          - required: false\n          - type: integer\n```\n```sh\n    Response:\n[{\n      \"caseId\": 3262,\n      \"authorizationId\": 5358,\n      \"authorizationNumber\": \"A2020412253690\",\n      \"authorizationType\": {\n        \"type\": \"AuthorizationType\",\n        \"id\": 11744,\n        \"key\": \"050:Repricing\",\n        \"description\": \"Arbitration\"\n      },\n      \"authorizationCategory\": {\n        \"type\": \"AuthorizationCategory\",\n        \"id\": 11716,\n        \"key\": \"069:DME\",\n        \"description\": \"Out of Network (OON)\"\n      },\n      \"facilityName\": \"\",\n      \"comments\": \"Major Medical:  No Deductible, No Coinsurance, No Copayment\",\n      \"authorizationStatus\": {\n        \"type\": \"AuthorizationStatus\",\n        \"id\": 1333,\n        \"key\": \"068:Waiting\",\n        \"description\": \"Approved\"\n      },\n      \"memberEligibility\": \"1618-1-0011820\",\n      \"diagnosisCodes\": [\n        {\n          \"code\": \"H26.229\",\n          \"description\": \"CATARACT SECONDARY TO OCULAR DISORDERS UNS EYE\",\n          \"primaryFlag\": false\n        }\n      ],\n      \"procedureCodes\": [\n        {\n          \"type\": \"CPT\",\n          \"code\": \"92018\",\n          \"description\": \"OPHTH XM&EVAL ANES W/WO MANJ GLOBE COMPL\"\n        },\n        {\n          \"type\": \"CPT\",\n          \"code\": \"67145\",\n          \"description\": \"PROPH RTA DTCHMNT W/O DRG 1/> SESS\"\n        }\n      ],\n      \"effectiveFromDate\": \"2020-08-24T03:00:00\",\n      \"effectiveToDate\": \"2020-08-24T03:00:00\",\n      \"createdDateTime\": \"2020-07-22T16:30:46.353Z\",\n      \"modifiedDateTime\": \"2020-07-22T16:30:46.353Z\"\n    },\n    {\n      \"caseId\": 3262,\n      \"authorizationId\": 2553,\n      \"authorizationNumber\": \"A1929815492132\",\n      \"authorizationType\": {\n        \"type\": \"AuthorizationType\",\n        \"id\": 11744,\n        \"key\": \"050:Repricing\",\n        \"description\": \"Arbitration\"\n      },\n      \"authorizationCategory\": {\n        \"type\": \"AuthorizationCategory\",\n        \"id\": 11717,\n        \"key\": \"069:TravelAir\",\n        \"description\": \"Preferred Provider Network (PPN)\"\n      },\n      \"facilityName\": \"\",\n      \"comments\": \"- Surgery; OPHTHALMOLOGICAL EXAM & EVAL, W/ ANESTHESIA, COMPLETE [92018]  - REMOVAL, VITREOUS, ANTERIOR APPROACH, PARTIAL REMOVAL [67005]  - EXTRACAPSULAR CATARACT REMOVAL W/ POSSIBLE INSERTION, LENS PROSTHESIS, COMPLEX [66982]  - SEVERING ADHESIONS, ANTERIOR SEGMENT, EYE, INCISIONAL (SEP PROC), POSTERIOR SYNECHIAE [65875]\",\n      \"authorizationStatus\": {\n        \"type\": \"AuthorizationStatus\",\n        \"id\": 1333,\n        \"key\": \"068:Waiting\",\n        \"description\": \"Approved\"\n      },\n      \"memberEligibility\": \"1618-1-0011820\",\n      \"diagnosisCodes\": [\n        {\n          \"code\": \"H20.023\",\n          \"description\": \"RECURRENT ACUTE IRIDOCYCLITIS BILATERAL\",\n          \"primaryFlag\": false\n        },\n        {\n          \"code\": \"H26.222\",\n          \"description\": \"CATARACT SECONDARY TO OCULAR DISORDERS LEFT EYE\",\n          \"primaryFlag\": true\n        }\n      ],\n      \"procedureCodes\": [\n        {\n          \"type\": \"CPT\",\n          \"code\": \"92018\",\n          \"description\": \"OPHTH XM&EVAL ANES W/WO MANJ GLOBE COMPL\"\n        },\n        {\n          \"type\": \"CPT\",\n          \"code\": \"67005\",\n          \"description\": \"RMVL VITREOUS ANT APPR PARTIAL REMOVAL\"\n        },\n        {\n          \"type\": \"CPT\",\n          \"code\": \"66982\",\n          \"description\": \"XCAPSULAR CATARACT RMVL INSJ LENS PROSTH 1 STG\"\n        },\n        {\n          \"type\": \"CPT\",\n          \"code\": \"65875\",\n          \"description\": \"SEVERING ADS ANT SEG INCAL SPX POST SYNECHIAE\"\n        }\n      ],\n      \"effectiveFromDate\": \"2019-05-20T03:00:00\",\n      \"effectiveToDate\": \"2019-05-20T03:00:00\",\n      \"createdDateTime\": \"2019-10-25T18:51:07.067Z\",\n      \"modifiedDateTime\": \"2020-11-03T14:07:18.210Z\"\n    }\n]\n```\n    POST   /v1/cases/{caseId}/authorizations/{authorizationId}\n    Description: Update an authorization on a Case\n```sh\n    Request:\n      - uri params: \n        - caseId: 1234\n        - authorizationId: 123456\n      - body:\n        - {\n            \"authorizationId\": 1234,\n            \"comments\": \"\",\n            \"status\": \"Pending\"\n          } \n```\n```sh\n    Response:\n```\n    GET   /v1/cases\n    Description: Get Case Summary by Client Id\n\n```sh\n    Request:\n      - query params:\n        - clientId:\n          - required: true\n          - type: integer\n        - requestedDateTime:\n          - required: false\n          - type: dateTime\n          - format: rfc3339\n        - offset:\n          - description: Skip over a number of elements by specifying an offset value for the query\n          - required: false\n          - type: integer\n        - limit:\n          - description: Limit the number of elements on the response\n          - required: false\n          - type: integer\n```\n```sh\n    Response:\n[\n    {\n      \"clientId\": \"1001\",\n      \"caseId\": 3972,\n      \"caseMember\": {\n        \"type\": \"Member\",\n        \"memberId\": 14,\n        \"memberFirstName\": \"Gabriela\",\n        \"memberLastName\": \"Cristantos Medina\",\n        \"memberDOB\": \"1983-11-13T04:00:00\"\n      },\n      \"caseNumber\": \"20201106-002\",\n      \"startDate\": \"2020-11-06T04:00:00\",\n      \"diagnosisCodes\": [\n        {\n          \"code\": \"E10.9\",\n          \"description\": \"TYPE 1 DIABETES MELLITUS WITHOUT COMPLICATIONS\",\n          \"primaryFlag\": true\n        }\n      ],\n      \"estimateEntryDate\": \"2020-11-06T04:00:00\",\n      \"consentReceivedDate\": \"2020-11-06T04:00:00\",\n      \"caseManager\": \"Gemma Sinclair\",\n      \"medicalPlan\": \"\",\n      \"costEstimate\": \"1200.00\",\n      \"treatingPhysician\": \"\",\n      \"facility\": \"\",\n      \"chargedAmount\": 0,\n      \"paidAmount\": 0,\n      \"repricedAmount\": 0,\n      \"savingsAmount\": 0,\n      \"caseStatus\": {\n        \"type\": \"CaseStatus\",\n        \"id\": 382,\n        \"key\": \"045:C-Progress\",\n        \"description\": \"In Process\"\n      },\n      \"createdDateTime\": \"2020-11-06T14:09:04.067Z\",\n      \"modifiedDateTime\": \"2020-11-06T14:17:58.693Z\"\n    }\n]    \n```\n    GET   /v1/cases/{caseId}/documents\n    Description: Get ALL Documents for a Case\n\n```sh\n    Request:\n      - uri params: \n        - caseId: 1234\n      - query params:\n        - requestedDateTime:\n          - required: false\n          - type: dateTime\n          - format: rfc3339\n        - offset:\n          - description: Skip over a number of elements by specifying an offset value for the query\n          - required: false\n          - type: integer\n        - limit:\n          - description: Limit the number of elements on the response\n          - required: false\n          - type: integer\n```\n```sh\n    Response:\n[\n  {\n    \"caseId\":3379,\n    \"documentId\":8126,\n    \"name\":\"HIAB Referral John Doran\",\n    \"fileType\":\"pdf\",\n    \"createdDateTime\":\"2020-07-21T14:50:34.680Z\",\n    \"modifiedDateTime\":\"2020-07-21T14:50:34.680Z\"\n  },\n  {\n    \"caseId\":3379,\n    \"documentId\":8273,\n    \"documentType\":{\n      \"type\":\"DocumentType\",\n      \"id\":11783,\n      \"key\":\"065:LOA\",\n      \"description\":\"Letter of Authorization (LOA)\"\n    },\n    \"name\":\"-LOA John Doran- Dr. Parazin\",\n    \"fileType\":\"pdf\",\n    \"createdDateTime\":\"2020-07-28T19:19:10.653Z\",\n    \"modifiedDateTime\":\"2020-07-28T19:19:10.653Z\"\n  }\n]    \n```",
    "x-amf-title": "Experience-case-api"
  },
  "paths": {
    "/v1": {},
    "/v1/healthcheck": {
      "get": {
        "description": "Common method used across all the API's, returns health of API. Return Status 200 and success if the APi is Running and accepting requests.",
        "produces": [
          "application/json"
        ],
        "responses": {
          "200": {
            "description": "",
            "x-amf-mediaType": "application/json",
            "schema": {
              "$ref": "#/definitions/type"
            }
          },
          "401": {
            "description": "",
            "x-amf-mediaType": "application/json",
            "schema": {
              "$ref": "#/definitions/type_1"
            }
          },
          "403": {
            "description": "",
            "x-amf-mediaType": "application/json",
            "schema": {
              "$ref": "#/definitions/type_1"
            }
          },
          "405": {
            "description": "",
            "x-amf-mediaType": "application/json",
            "schema": {
              "$ref": "#/definitions/type_1"
            }
          },
          "500": {
            "description": "",
            "x-amf-mediaType": "application/json",
            "schema": {
              "$ref": "#/definitions/type_1"
            }
          }
        }
      }
    },
    "/v1/cases": {
      "get": {
        "description": "Get Cases by Id",
        "consumes": [
          "application/json"
        ],
        "produces": [
          "application/json"
        ],
        "parameters": [
          {
            "name": "clientId",
            "required": true,
            "in": "query",
            "type": "integer"
          },
          {
            "name": "requestedDateTime",
            "in": "query",
            "type": "string"
          },
          {
            "name": "offset",
            "description": "Skip over a number of elements by specifying an offset value for the query",
            "required": false,
            "in": "query",
            "default": 0,
            "type": "integer"
          },
          {
            "name": "limit",
            "description": "Limit the number of elements on the response",
            "required": false,
            "in": "query",
            "default": 10,
            "type": "integer"
          },
          {
            "name": "client_id",
            "description": "The Client ID allocated by MuleSoft when you request access.",
            "required": true,
            "in": "header",
            "type": "string"
          },
          {
            "name": "client_secret",
            "description": "The Client Secret allocated by MuleSoft when you request access.",
            "required": true,
            "in": "header",
            "type": "string"
          },
          {
            "name": "X-Forwarded-For",
            "description": "This is the originating IP address of a client.",
            "required": true,
            "in": "header",
            "type": "string"
          },
          {
            "name": "X-Correlation-ID",
            "description": "This is a UUID or GUID used for the tracking and filtering of requests.",
            "required": true,
            "in": "header",
            "type": "string",
            "pattern": "^.{16,}$"
          }
        ],
        "responses": {
          "200": {
            "description": "",
            "x-amf-mediaType": "application/json",
            "schema": {
              "example": [
                {
                  "clientId": "1001",
                  "caseId": 3972,
                  "caseMember": {
                    "type": "Member",
                    "memberId": 14,
                    "memberFirstName": "Gabriela",
                    "memberLastName": "Cristantos Medina",
                    "memberDOB": "1983-11-13T04:00:00"
                  },
                  "caseNumber": "20201106-002",
                  "startDate": "2020-11-06T04:00:00",
                  "diagnosisCodes": [
                    {
                      "code": "E10.9",
                      "description": "TYPE 1 DIABETES MELLITUS WITHOUT COMPLICATIONS",
                      "primaryFlag": true
                    }
                  ],
                  "estimateEntryDate": "2020-11-06T04:00:00",
                  "caseManager": "Gemma Sinclair",
                  "medicalPlan": "",
                  "costEstimate": "1200.00",
                  "treatingPhysician": "",
                  "facility": "",
                  "chargedAmount": 0,
                  "paidAmount": 0,
                  "repricedAmount": 0,
                  "savingsAmount": 0,
                  "caseStatus": {
                    "type": "CaseStatus",
                    "id": 382,
                    "key": "045:C-Progress",
                    "description": "In Process"
                  },
                  "createdDateTime": "2020-11-06T14:09:04.067Z",
                  "modifiedDateTime": "2020-11-06T14:17:58.693Z"
                }
              ],
              "type": "array",
              "items": {
                "$ref": "#/definitions/case"
              }
            }
          },
          "404": {
            "description": "",
            "x-amf-mediaType": "application/json",
            "schema": {
              "$ref": "#/definitions/type_1"
            }
          },
          "401": {
            "description": "",
            "x-amf-mediaType": "application/json",
            "schema": {
              "$ref": "#/definitions/type_1"
            }
          },
          "403": {
            "description": "",
            "x-amf-mediaType": "application/json",
            "schema": {
              "$ref": "#/definitions/type_1"
            }
          },
          "405": {
            "description": "",
            "x-amf-mediaType": "application/json",
            "schema": {
              "$ref": "#/definitions/type_1"
            }
          },
          "500": {
            "description": "",
            "x-amf-mediaType": "application/json",
            "schema": {
              "$ref": "#/definitions/type_1"
            }
          }
        }
      }
    },
    "/v1/cases/{caseId}": {
      "parameters": [
        {
          "name": "caseId",
          "description": "Search by CaseId.",
          "required": true,
          "in": "path",
          "type": "number"
        }
      ]
    },
    "/v1/cases/{caseId}/notes": {
      "get": {
        "description": "Get all Case Notes",
        "consumes": [
          "application/json"
        ],
        "produces": [
          "application/json"
        ],
        "parameters": [
          {
            "name": "requestedDateTime",
            "in": "query",
            "type": "string"
          },
          {
            "name": "offset",
            "description": "Skip over a number of elements by specifying an offset value for the query",
            "required": false,
            "in": "query",
            "default": 0,
            "type": "integer"
          },
          {
            "name": "limit",
            "description": "Limit the number of elements on the response",
            "required": false,
            "in": "query",
            "default": 10,
            "type": "integer"
          },
          {
            "name": "caseId",
            "description": "Search by CaseId.",
            "required": true,
            "in": "path",
            "type": "number"
          },
          {
            "name": "client_id",
            "description": "The Client ID allocated by MuleSoft when you request access.",
            "required": true,
            "in": "header",
            "type": "string"
          },
          {
            "name": "client_secret",
            "description": "The Client Secret allocated by MuleSoft when you request access.",
            "required": true,
            "in": "header",
            "type": "string"
          },
          {
            "name": "X-Forwarded-For",
            "description": "This is the originating IP address of a client.",
            "required": true,
            "in": "header",
            "type": "string"
          },
          {
            "name": "X-Correlation-ID",
            "description": "This is a UUID or GUID used for the tracking and filtering of requests.",
            "required": true,
            "in": "header",
            "type": "string",
            "pattern": "^.{16,}$"
          }
        ],
        "responses": {
          "200": {
            "description": "",
            "x-amf-mediaType": "application/json",
            "schema": {
              "example": [
                {
                  "caseId": 3974,
                  "noteId": 2941,
                  "type": "Note",
                  "noteType": {
                    "type": "NoteType",
                    "id": 11903,
                    "key": "030:carrier",
                    "description": "Carrier Note"
                  },
                  "note": "Air lift needed to John Smith immediately in relation to approved auth",
                  "noteAuthor": "One Team Health",
                  "noteCreatedDate": "2020-11-18T04:00:00",
                  "direction": "Inbound",
                  "code": "Email",
                  "caller": "",
                  "callee": "",
                  "createdDateTime": "2020-11-18T13:32:58.470Z",
                  "modifiedDateTime": "2020-11-18T13:32:58.470Z"
                },
                {
                  "caseId": 3974,
                  "noteId": 2943,
                  "type": "Note",
                  "noteType": {
                    "type": "NoteType",
                    "id": 11903,
                    "key": "030:carrier",
                    "description": "Carrier Note"
                  },
                  "note": "Medical notes Fallon Serv",
                  "noteAuthor": "One Team Health",
                  "noteCreatedDate": "2020-11-18T04:00:00",
                  "direction": "Inbound",
                  "code": "Email",
                  "caller": "",
                  "callee": "",
                  "createdDateTime": "2020-11-18T16:57:39.397Z",
                  "modifiedDateTime": "2020-11-18T16:57:39.397Z"
                },
                {
                  "caseId": 3974,
                  "noteId": 2948,
                  "type": "Note",
                  "noteType": {
                    "type": "NoteType",
                    "id": 11903,
                    "key": "030:carrier",
                    "description": "Carrier Note"
                  },
                  "note": "Medical notes Fallon Serv",
                  "noteAuthor": "One Team Health",
                  "noteCreatedDate": "2020-11-18T04:00:00",
                  "direction": "Inbound",
                  "code": "Email",
                  "caller": "",
                  "callee": "",
                  "createdDateTime": "2020-11-18T19:36:28.733Z",
                  "modifiedDateTime": "2020-11-18T19:36:28.733Z"
                }
              ],
              "type": "array",
              "items": {
                "$ref": "#/definitions/caseNote"
              }
            }
          },
          "404": {
            "description": "",
            "x-amf-mediaType": "application/json",
            "schema": {
              "$ref": "#/definitions/type_1"
            }
          },
          "401": {
            "description": "",
            "x-amf-mediaType": "application/json",
            "schema": {
              "$ref": "#/definitions/type_1"
            }
          },
          "403": {
            "description": "",
            "x-amf-mediaType": "application/json",
            "schema": {
              "$ref": "#/definitions/type_1"
            }
          },
          "405": {
            "description": "",
            "x-amf-mediaType": "application/json",
            "schema": {
              "$ref": "#/definitions/type_1"
            }
          },
          "500": {
            "description": "",
            "x-amf-mediaType": "application/json",
            "schema": {
              "$ref": "#/definitions/type_1"
            }
          }
        }
      },
      "post": {
        "description": "Create Case Note",
        "consumes": [
          "application/json"
        ],
        "produces": [
          "application/json"
        ],
        "parameters": [
          {
            "name": "caseId",
            "description": "Search by CaseId.",
            "required": true,
            "in": "path",
            "type": "number"
          },
          {
            "name": "client_id",
            "description": "The Client ID allocated by MuleSoft when you request access.",
            "required": true,
            "in": "header",
            "type": "string"
          },
          {
            "name": "client_secret",
            "description": "The Client Secret allocated by MuleSoft when you request access.",
            "required": true,
            "in": "header",
            "type": "string"
          },
          {
            "name": "X-Forwarded-For",
            "description": "This is the originating IP address of a client.",
            "required": true,
            "in": "header",
            "type": "string"
          },
          {
            "name": "X-Correlation-ID",
            "description": "This is a UUID or GUID used for the tracking and filtering of requests.",
            "required": true,
            "in": "header",
            "type": "string",
            "pattern": "^.{16,}$"
          },
          {
            "x-amf-mediaType": "application/json",
            "in": "body",
            "name": "generated",
            "schema": {
              "$ref": "#/definitions/caseNotePost"
            }
          }
        ],
        "responses": {
          "201": {
            "description": "",
            "x-amf-mediaType": "application/json",
            "schema": {}
          },
          "202": {
            "description": "",
            "x-amf-mediaType": "application/json",
            "schema": {}
          },
          "400": {
            "description": "",
            "x-amf-mediaType": "application/json",
            "schema": {
              "$ref": "#/definitions/type_1"
            }
          },
          "401": {
            "description": "",
            "x-amf-mediaType": "application/json",
            "schema": {
              "$ref": "#/definitions/type_1"
            }
          },
          "403": {
            "description": "",
            "x-amf-mediaType": "application/json",
            "schema": {
              "$ref": "#/definitions/type_1"
            }
          },
          "405": {
            "description": "",
            "x-amf-mediaType": "application/json",
            "schema": {
              "$ref": "#/definitions/type_1"
            }
          },
          "500": {
            "description": "",
            "x-amf-mediaType": "application/json",
            "schema": {
              "$ref": "#/definitions/type_1"
            }
          }
        }
      }
    },
    "/v1/cases/{caseId}/tasks": {
      "get": {
        "description": "Get all Case Tasks",
        "consumes": [
          "application/json"
        ],
        "produces": [
          "application/json"
        ],
        "parameters": [
          {
            "name": "requestedDateTime",
            "in": "query",
            "type": "string"
          },
          {
            "name": "offset",
            "description": "Skip over a number of elements by specifying an offset value for the query",
            "required": false,
            "in": "query",
            "default": 0,
            "type": "integer"
          },
          {
            "name": "limit",
            "description": "Limit the number of elements on the response",
            "required": false,
            "in": "query",
            "default": 10,
            "type": "integer"
          },
          {
            "name": "caseId",
            "description": "Search by CaseId.",
            "required": true,
            "in": "path",
            "type": "number"
          },
          {
            "name": "client_id",
            "description": "The Client ID allocated by MuleSoft when you request access.",
            "required": true,
            "in": "header",
            "type": "string"
          },
          {
            "name": "client_secret",
            "description": "The Client Secret allocated by MuleSoft when you request access.",
            "required": true,
            "in": "header",
            "type": "string"
          },
          {
            "name": "X-Forwarded-For",
            "description": "This is the originating IP address of a client.",
            "required": true,
            "in": "header",
            "type": "string"
          },
          {
            "name": "X-Correlation-ID",
            "description": "This is a UUID or GUID used for the tracking and filtering of requests.",
            "required": true,
            "in": "header",
            "type": "string",
            "pattern": "^.{16,}$"
          }
        ],
        "responses": {
          "200": {
            "description": "",
            "x-amf-mediaType": "application/json",
            "schema": {
              "example": [
                {
                  "caseId": 3261,
                  "taskId": 5883,
                  "taskType": {
                    "type": "TaskType",
                    "id": 2050,
                    "key": "TSK:2050",
                    "description": "Assign Case"
                  },
                  "startDate": "2020-07-02T03:00:00",
                  "completedDate": "2020-07-02T03:00:00",
                  "dueDate": "2020-07-03T03:00:00",
                  "taskStatus": {
                    "type": "TaskStatus",
                    "id": 426,
                    "key": "048:T-Completed",
                    "description": "Completed"
                  },
                  "createdDateTime": "2020-07-02T12:15:01.473Z",
                  "modifiedDateTime": "2020-07-02T12:15:01.473Z",
                  "taskPriority": {
                    "type": "TaskPriority",
                    "id": 426,
                    "key": "004:Medium",
                    "description": "Medium"
                  }
                }
              ],
              "type": "array",
              "items": {
                "$ref": "#/definitions/caseTasks"
              }
            }
          },
          "404": {
            "description": "",
            "x-amf-mediaType": "application/json",
            "schema": {
              "$ref": "#/definitions/type_1"
            }
          },
          "401": {
            "description": "",
            "x-amf-mediaType": "application/json",
            "schema": {
              "$ref": "#/definitions/type_1"
            }
          },
          "403": {
            "description": "",
            "x-amf-mediaType": "application/json",
            "schema": {
              "$ref": "#/definitions/type_1"
            }
          },
          "405": {
            "description": "",
            "x-amf-mediaType": "application/json",
            "schema": {
              "$ref": "#/definitions/type_1"
            }
          },
          "500": {
            "description": "",
            "x-amf-mediaType": "application/json",
            "schema": {
              "$ref": "#/definitions/type_1"
            }
          }
        }
      },
      "post": {
        "description": "Create Case Tasks",
        "consumes": [
          "application/json"
        ],
        "produces": [
          "application/json"
        ],
        "parameters": [
          {
            "name": "caseId",
            "description": "Search by CaseId.",
            "required": true,
            "in": "path",
            "type": "number"
          },
          {
            "name": "client_id",
            "description": "The Client ID allocated by MuleSoft when you request access.",
            "required": true,
            "in": "header",
            "type": "string"
          },
          {
            "name": "client_secret",
            "description": "The Client Secret allocated by MuleSoft when you request access.",
            "required": true,
            "in": "header",
            "type": "string"
          },
          {
            "name": "X-Forwarded-For",
            "description": "This is the originating IP address of a client.",
            "required": true,
            "in": "header",
            "type": "string"
          },
          {
            "name": "X-Correlation-ID",
            "description": "This is a UUID or GUID used for the tracking and filtering of requests.",
            "required": true,
            "in": "header",
            "type": "string",
            "pattern": "^.{16,}$"
          },
          {
            "x-amf-mediaType": "application/json",
            "in": "body",
            "name": "generated",
            "schema": {
              "$ref": "#/definitions/caseTaskPost"
            }
          }
        ],
        "responses": {
          "201": {
            "description": "",
            "x-amf-mediaType": "application/json",
            "schema": {}
          },
          "202": {
            "description": "",
            "x-amf-mediaType": "application/json",
            "schema": {}
          },
          "400": {
            "description": "",
            "x-amf-mediaType": "application/json",
            "schema": {
              "$ref": "#/definitions/type_1"
            }
          },
          "401": {
            "description": "",
            "x-amf-mediaType": "application/json",
            "schema": {
              "$ref": "#/definitions/type_1"
            }
          },
          "403": {
            "description": "",
            "x-amf-mediaType": "application/json",
            "schema": {
              "$ref": "#/definitions/type_1"
            }
          },
          "405": {
            "description": "",
            "x-amf-mediaType": "application/json",
            "schema": {
              "$ref": "#/definitions/type_1"
            }
          },
          "500": {
            "description": "",
            "x-amf-mediaType": "application/json",
            "schema": {
              "$ref": "#/definitions/type_1"
            }
          }
        }
      }
    },
    "/v1/cases/{caseId}/authorizations": {
      "get": {
        "description": "Get all Case Authorizations",
        "consumes": [
          "application/json"
        ],
        "produces": [
          "application/json"
        ],
        "parameters": [
          {
            "name": "requestedDateTime",
            "in": "query",
            "type": "string"
          },
          {
            "name": "offset",
            "description": "Skip over a number of elements by specifying an offset value for the query",
            "required": false,
            "in": "query",
            "default": 0,
            "type": "integer"
          },
          {
            "name": "limit",
            "description": "Limit the number of elements on the response",
            "required": false,
            "in": "query",
            "default": 10,
            "type": "integer"
          },
          {
            "name": "caseId",
            "description": "Search by CaseId.",
            "required": true,
            "in": "path",
            "type": "number"
          },
          {
            "name": "client_id",
            "description": "The Client ID allocated by MuleSoft when you request access.",
            "required": true,
            "in": "header",
            "type": "string"
          },
          {
            "name": "client_secret",
            "description": "The Client Secret allocated by MuleSoft when you request access.",
            "required": true,
            "in": "header",
            "type": "string"
          },
          {
            "name": "X-Forwarded-For",
            "description": "This is the originating IP address of a client.",
            "required": true,
            "in": "header",
            "type": "string"
          },
          {
            "name": "X-Correlation-ID",
            "description": "This is a UUID or GUID used for the tracking and filtering of requests.",
            "required": true,
            "in": "header",
            "type": "string",
            "pattern": "^.{16,}$"
          }
        ],
        "responses": {
          "200": {
            "description": "",
            "x-amf-mediaType": "application/json",
            "schema": {
              "example": [
                {
                  "caseId": 3262,
                  "authorizationId": 5358,
                  "authorizationNumber": "A2020412253690",
                  "authorizationType": {
                    "type": "AuthorizationType",
                    "id": 11744,
                    "key": "050:Repricing",
                    "description": "Arbitration"
                  },
                  "authorizationCategory": {
                    "type": "AuthorizationCategory",
                    "id": 11716,
                    "key": "069:DME",
                    "description": "Out of Network (OON)"
                  },
                  "facilityName": "",
                  "comments": "Major Medical:  No Deductible, No Coinsurance, No Copayment",
                  "authorizationStatus": {
                    "type": "AuthorizationStatus",
                    "id": 1333,
                    "key": "068:Waiting",
                    "description": "Approved"
                  },
                  "memberEligibility": "1618-1-0011820",
                  "diagnosisCodes": [
                    {
                      "code": "H26.229",
                      "description": "CATARACT SECONDARY TO OCULAR DISORDERS UNS EYE",
                      "primaryFlag": false
                    }
                  ],
                  "procedureCodes": [
                    {
                      "type": "CPT",
                      "code": "92018",
                      "description": "OPHTH XM&EVAL ANES W/WO MANJ GLOBE COMPL"
                    },
                    {
                      "type": "CPT",
                      "code": "67145",
                      "description": "PROPH RTA DTCHMNT W/O DRG 1/> SESS"
                    }
                  ],
                  "effectiveFromDate": "2020-08-24T03:00:00",
                  "effectiveToDate": "2020-08-24T03:00:00",
                  "createdDateTime": "2020-07-22T16:30:46.353Z",
                  "modifiedDateTime": "2020-07-22T16:30:46.353Z"
                },
                {
                  "caseId": 3262,
                  "authorizationId": 2553,
                  "authorizationNumber": "A1929815492132",
                  "authorizationType": {
                    "type": "AuthorizationType",
                    "id": 11744,
                    "key": "050:Repricing",
                    "description": "Arbitration"
                  },
                  "authorizationCategory": {
                    "type": "AuthorizationCategory",
                    "id": 11717,
                    "key": "069:TravelAir",
                    "description": "Preferred Provider Network (PPN)"
                  },
                  "facilityName": "",
                  "comments": "- Surgery; OPHTHALMOLOGICAL EXAM & EVAL, W/ ANESTHESIA, COMPLETE [92018]  - REMOVAL, VITREOUS, ANTERIOR APPROACH, PARTIAL REMOVAL [67005]  - EXTRACAPSULAR CATARACT REMOVAL W/ POSSIBLE INSERTION, LENS PROSTHESIS, COMPLEX [66982]  - SEVERING ADHESIONS, ANTERIOR SEGMENT, EYE, INCISIONAL (SEP PROC), POSTERIOR SYNECHIAE [65875]",
                  "authorizationStatus": {
                    "type": "AuthorizationStatus",
                    "id": 1333,
                    "key": "068:Waiting",
                    "description": "Approved"
                  },
                  "memberEligibility": "1618-1-0011820",
                  "diagnosisCodes": [
                    {
                      "code": "H20.023",
                      "description": "RECURRENT ACUTE IRIDOCYCLITIS BILATERAL",
                      "primaryFlag": false
                    },
                    {
                      "code": "H26.222",
                      "description": "CATARACT SECONDARY TO OCULAR DISORDERS LEFT EYE",
                      "primaryFlag": true
                    }
                  ],
                  "procedureCodes": [
                    {
                      "type": "CPT",
                      "code": "92018",
                      "description": "OPHTH XM&EVAL ANES W/WO MANJ GLOBE COMPL"
                    },
                    {
                      "type": "CPT",
                      "code": "67005",
                      "description": "RMVL VITREOUS ANT APPR PARTIAL REMOVAL"
                    },
                    {
                      "type": "CPT",
                      "code": "66982",
                      "description": "XCAPSULAR CATARACT RMVL INSJ LENS PROSTH 1 STG"
                    },
                    {
                      "type": "CPT",
                      "code": "65875",
                      "description": "SEVERING ADS ANT SEG INCAL SPX POST SYNECHIAE"
                    }
                  ],
                  "effectiveFromDate": "2019-05-20T03:00:00",
                  "effectiveToDate": "2019-05-20T03:00:00",
                  "createdDateTime": "2019-10-25T18:51:07.067Z",
                  "modifiedDateTime": "2020-11-03T14:07:18.210Z"
                }
              ],
              "type": "array",
              "items": {
                "$ref": "#/definitions/caseAuthorization"
              }
            }
          },
          "404": {
            "description": "",
            "x-amf-mediaType": "application/json",
            "schema": {
              "$ref": "#/definitions/type_1"
            }
          },
          "401": {
            "description": "",
            "x-amf-mediaType": "application/json",
            "schema": {
              "$ref": "#/definitions/type_1"
            }
          },
          "403": {
            "description": "",
            "x-amf-mediaType": "application/json",
            "schema": {
              "$ref": "#/definitions/type_1"
            }
          },
          "405": {
            "description": "",
            "x-amf-mediaType": "application/json",
            "schema": {
              "$ref": "#/definitions/type_1"
            }
          },
          "500": {
            "description": "",
            "x-amf-mediaType": "application/json",
            "schema": {
              "$ref": "#/definitions/type_1"
            }
          }
        }
      }
    },
    "/v1/cases/{caseId}/authorizations/{authorizationId}": {
      "patch": {
        "description": "Partial update Case Authorization by Id",
        "consumes": [
          "application/json"
        ],
        "produces": [
          "application/json"
        ],
        "parameters": [
          {
            "name": "caseId",
            "description": "Search by CaseId.",
            "required": true,
            "in": "path",
            "type": "number"
          },
          {
            "name": "authorizationId",
            "description": "AuthorizationId.",
            "required": true,
            "in": "path",
            "type": "number"
          },
          {
            "name": "client_id",
            "description": "The Client ID allocated by MuleSoft when you request access.",
            "required": true,
            "in": "header",
            "type": "string"
          },
          {
            "name": "client_secret",
            "description": "The Client Secret allocated by MuleSoft when you request access.",
            "required": true,
            "in": "header",
            "type": "string"
          },
          {
            "name": "X-Forwarded-For",
            "description": "This is the originating IP address of a client.",
            "required": true,
            "in": "header",
            "type": "string"
          },
          {
            "name": "X-Correlation-ID",
            "description": "This is a UUID or GUID used for the tracking and filtering of requests.",
            "required": true,
            "in": "header",
            "type": "string",
            "pattern": "^.{16,}$"
          },
          {
            "x-amf-mediaType": "application/json",
            "in": "body",
            "name": "generated",
            "schema": {
              "$ref": "#/definitions/caseAuthorizationUpdate"
            }
          }
        ],
        "responses": {
          "200": {
            "description": "",
            "x-amf-mediaType": "application/json",
            "schema": {}
          },
          "202": {
            "description": "",
            "x-amf-mediaType": "application/json",
            "schema": {}
          },
          "400": {
            "description": "",
            "x-amf-mediaType": "application/json",
            "schema": {
              "$ref": "#/definitions/type_1"
            }
          },
          "401": {
            "description": "",
            "x-amf-mediaType": "application/json",
            "schema": {
              "$ref": "#/definitions/type_1"
            }
          },
          "403": {
            "description": "",
            "x-amf-mediaType": "application/json",
            "schema": {
              "$ref": "#/definitions/type_1"
            }
          },
          "405": {
            "description": "",
            "x-amf-mediaType": "application/json",
            "schema": {
              "$ref": "#/definitions/type_1"
            }
          },
          "500": {
            "description": "",
            "x-amf-mediaType": "application/json",
            "schema": {
              "$ref": "#/definitions/type_1"
            }
          }
        }
      }
    },
    "/v1/cases/{caseId}/documents": {
      "get": {
        "description": "Get all Case documents",
        "consumes": [
          "application/json"
        ],
        "produces": [
          "application/json"
        ],
        "parameters": [
          {
            "name": "requestedDateTime",
            "in": "query",
            "type": "string"
          },
          {
            "name": "offset",
            "description": "Skip over a number of elements by specifying an offset value for the query",
            "required": false,
            "in": "query",
            "default": 0,
            "type": "integer"
          },
          {
            "name": "limit",
            "description": "Limit the number of elements on the response",
            "required": false,
            "in": "query",
            "default": 10,
            "type": "integer"
          },
          {
            "name": "caseId",
            "description": "Search by CaseId.",
            "required": true,
            "in": "path",
            "type": "number"
          },
          {
            "name": "client_id",
            "description": "The Client ID allocated by MuleSoft when you request access.",
            "required": true,
            "in": "header",
            "type": "string"
          },
          {
            "name": "client_secret",
            "description": "The Client Secret allocated by MuleSoft when you request access.",
            "required": true,
            "in": "header",
            "type": "string"
          },
          {
            "name": "X-Forwarded-For",
            "description": "This is the originating IP address of a client.",
            "required": true,
            "in": "header",
            "type": "string"
          },
          {
            "name": "X-Correlation-ID",
            "description": "This is a UUID or GUID used for the tracking and filtering of requests.",
            "required": true,
            "in": "header",
            "type": "string",
            "pattern": "^.{16,}$"
          }
        ],
        "responses": {
          "200": {
            "description": "",
            "x-amf-mediaType": "application/json",
            "schema": {
              "example": [
                {
                  "caseId": 3379,
                  "documentId": 8126,
                  "name": "HIAB Referral John Doran",
                  "fileType": "pdf",
                  "createdDateTime": "2020-07-21T14:50:34.680Z",
                  "modifiedDateTime": "2020-07-21T14:50:34.680Z"
                },
                {
                  "caseId": 3379,
                  "documentId": 8273,
                  "documentType": {
                    "type": "DocumentType",
                    "id": 11783,
                    "key": "065:LOA",
                    "description": "Letter of Authorization (LOA)"
                  },
                  "name": "-LOA John Doran- Dr. Parazin",
                  "fileType": "pdf",
                  "createdDateTime": "2020-07-28T19:19:10.653Z",
                  "modifiedDateTime": "2020-07-28T19:19:10.653Z"
                }
              ],
              "type": "array",
              "items": {
                "$ref": "#/definitions/caseDocument"
              }
            }
          },
          "404": {
            "description": "",
            "x-amf-mediaType": "application/json",
            "schema": {
              "$ref": "#/definitions/type_1"
            }
          },
          "401": {
            "description": "",
            "x-amf-mediaType": "application/json",
            "schema": {
              "$ref": "#/definitions/type_1"
            }
          },
          "403": {
            "description": "",
            "x-amf-mediaType": "application/json",
            "schema": {
              "$ref": "#/definitions/type_1"
            }
          },
          "405": {
            "description": "",
            "x-amf-mediaType": "application/json",
            "schema": {
              "$ref": "#/definitions/type_1"
            }
          },
          "500": {
            "description": "",
            "x-amf-mediaType": "application/json",
            "schema": {
              "$ref": "#/definitions/type_1"
            }
          }
        }
      }
    },
    "/v1/cases/{caseId}/documents/{documentId}": {
      "get": {
        "description": "Get the file content",
        "consumes": [
          "application/json"
        ],
        "produces": [
          "application/json"
        ],
        "parameters": [
          {
            "name": "caseId",
            "description": "Search by CaseId.",
            "required": true,
            "in": "path",
            "type": "number"
          },
          {
            "name": "documentId",
            "description": "Document Id",
            "required": true,
            "in": "path",
            "type": "number"
          },
          {
            "name": "client_id",
            "description": "The Client ID allocated by MuleSoft when you request access.",
            "required": true,
            "in": "header",
            "type": "string"
          },
          {
            "name": "client_secret",
            "description": "The Client Secret allocated by MuleSoft when you request access.",
            "required": true,
            "in": "header",
            "type": "string"
          },
          {
            "name": "X-Forwarded-For",
            "description": "This is the originating IP address of a client.",
            "required": true,
            "in": "header",
            "type": "string"
          },
          {
            "name": "X-Correlation-ID",
            "description": "This is a UUID or GUID used for the tracking and filtering of requests.",
            "required": true,
            "in": "header",
            "type": "string",
            "pattern": "^.{16,}$"
          }
        ],
        "responses": {
          "200": {
            "description": "",
            "x-amf-mediaType": "binary/octet-stream",
            "schema": {}
          },
          "404": {
            "description": "",
            "x-amf-mediaType": "application/json",
            "schema": {
              "$ref": "#/definitions/type_1"
            }
          },
          "401": {
            "description": "",
            "x-amf-mediaType": "application/json",
            "schema": {
              "$ref": "#/definitions/type_1"
            }
          },
          "403": {
            "description": "",
            "x-amf-mediaType": "application/json",
            "schema": {
              "$ref": "#/definitions/type_1"
            }
          },
          "405": {
            "description": "",
            "x-amf-mediaType": "application/json",
            "schema": {
              "$ref": "#/definitions/type_1"
            }
          },
          "500": {
            "description": "",
            "x-amf-mediaType": "application/json",
            "schema": {
              "$ref": "#/definitions/type_1"
            }
          }
        }
      }
    }
  },
  "definitions": {
    "type": {
      "example": {
        "message": "Success"
      },
      "type": "object",
      "additionalProperties": true,
      "required": [
        "message"
      ],
      "properties": {
        "message": {
          "type": "string"
        }
      }
    },
    "type_1": {
      "x-amf-examples": {
        "example_44": {
          "apiName": "hello-api",
          "version": "v1",
          "correlationId": "e2c58b60-5c10-11e9-88b4-645aede946d1",
          "timestamp": "2019-04-10T22:18:40.964-06:00",
          "errorDescription": "Resource not found"
        },
        "example_47": {
          "apiName": "hello-api",
          "version": "v1",
          "correlationId": "e2c58b60-5c10-11e9-88b4-645aede946d1",
          "timestamp": "2019-04-10T22:18:40.964-06:00",
          "errorDescription": "Method not allowed"
        },
        "example_34": {
          "apiName": "hello-api",
          "version": "v1",
          "correlationId": "e2c58b60-5c10-11e9-88b4-645aede946d1",
          "timestamp": "2019-04-10T22:18:40.964-06:00",
          "errorDescription": "Required field Id not provided in request"
        },
        "example_48": {
          "apiName": "hello-api",
          "version": "v1",
          "correlationId": "e2c58b60-5c10-11e9-88b4-645aede946d1",
          "timestamp": "2019-04-10T22:18:40.964-06:00",
          "errorDescription": "Internal server error"
        },
        "example_45": {
          "apiName": "hello-api",
          "version": "v1",
          "correlationId": "e2c58b60-5c10-11e9-88b4-645aede946d1",
          "timestamp": "2019-04-10T22:18:40.964-06:00",
          "errorDescription": "Access Denied"
        },
        "example_46": {
          "apiName": "hello-api",
          "version": "v1",
          "correlationId": "e2c58b60-5c10-11e9-88b4-645aede946d1",
          "timestamp": "2019-04-10T22:18:40.964-06:00",
          "errorDescription": "Forbidden"
        }
      },
      "type": "object",
      "additionalProperties": true,
      "required": [
        "apiName",
        "version",
        "correlationId",
        "errorDescription"
      ],
      "properties": {
        "apiName": {
          "type": "string"
        },
        "version": {
          "type": "string"
        },
        "correlationId": {
          "type": "string"
        },
        "errorDescription": {
          "type": "string"
        }
      }
    },
    "case": {
      "type": "object",
      "additionalProperties": true,
      "required": [
        "caseId"
      ],
      "properties": {
        "caseId": {
          "type": "number"
        },
        "clientId": {
          "type": "string"
        },
        "caseMember": {
          "$ref": "#/definitions/type_2"
        },
        "caseNumber": {
          "type": "string"
        },
        "startDate": {
          "type": "string"
        },
        "endDate": {
          "type": "string"
        },
        "diagnosisCodes": {
          "type": "array",
          "items": {
            "$ref": "#/definitions/items"
          }
        },
        "estimateEntryDate": {
          "type": "string"
        },
        "consentReceivedDate": {
          "type": "string"
        },
        "caseManager": {
          "type": "string"
        },
        "medicalPlan": {
          "type": "string"
        },
        "costEstimate": {
          "type": "string"
        },
        "treatingPhysician": {
          "type": "string"
        },
        "facility": {
          "type": "string"
        },
        "chargedAmount": {
          "type": "number"
        },
        "paidAmount": {
          "type": "number"
        },
        "repricedAmount": {
          "type": "number"
        },
        "savingsAmount": {
          "type": "number"
        },
        "caseStatus": {
          "$ref": "#/definitions/type_3"
        },
        "createdDateTime": {
          "type": "string"
        },
        "modifiedDateTime": {
          "type": "string"
        }
      }
    },
    "caseNote": {
      "type": "object",
      "additionalProperties": true,
      "required": [
        "caseId",
        "noteId",
        "type"
      ],
      "properties": {
        "caseId": {
          "type": "number"
        },
        "noteId": {
          "type": "number"
        },
        "type": {
          "type": "string"
        },
        "noteType": {
          "$ref": "#/definitions/type_3"
        },
        "noteCreatedDate": {
          "type": "string"
        },
        "note": {
          "type": "string"
        },
        "noteAuthor": {
          "type": "string"
        },
        "direction": {
          "type": "string"
        },
        "code": {
          "type": "string"
        },
        "caller": {
          "type": "string"
        },
        "callee": {
          "type": "string"
        },
        "createdDateTime": {
          "type": "string"
        },
        "modifiedDateTime": {
          "type": "string"
        }
      }
    },
    "caseNotePost": {
      "example": {
        "uuid": "a25f5974-e7df-43be-b048-23f55e29c971",
        "type": "Note",
        "note": "Lorem ipsum"
      },
      "type": "object",
      "additionalProperties": true,
      "required": [
        "uuid",
        "type",
        "note"
      ],
      "properties": {
        "uuid": {
          "type": "string"
        },
        "type": {
          "type": "string"
        },
        "note": {
          "type": "string"
        }
      }
    },
    "caseTasks": {
      "type": "object",
      "additionalProperties": true,
      "required": [
        "caseId",
        "taskId"
      ],
      "properties": {
        "caseId": {
          "type": "number"
        },
        "taskId": {
          "type": "number"
        },
        "taskType": {
          "$ref": "#/definitions/type_3"
        },
        "taskPriority": {
          "$ref": "#/definitions/type_3"
        },
        "startDate": {
          "type": "string"
        },
        "dueDate": {
          "type": "string"
        },
        "completedDate": {
          "type": "string"
        },
        "taskStatus": {
          "$ref": "#/definitions/type_3"
        },
        "createdDateTime": {
          "type": "string"
        },
        "modifiedDateTime": {
          "type": "string"
        }
      }
    },
    "caseTaskPost": {
      "example": {
        "uuid": "a25f5974-e7df-43be-b048-23f55e29c971",
        "type": "NNNNNNN",
        "priority": "High",
        "startDate": "2020-06-01T10:30:00.000Z"
      },
      "type": "object",
      "additionalProperties": true,
      "required": [
        "uuid",
        "type",
        "priority",
        "startDate"
      ],
      "properties": {
        "uuid": {
          "type": "string"
        },
        "type": {
          "type": "string"
        },
        "priority": {
          "type": "string"
        },
        "startDate": {
          "type": "string"
        }
      }
    },
    "caseAuthorization": {
      "type": "object",
      "additionalProperties": true,
      "required": [
        "caseId",
        "authorizationId"
      ],
      "properties": {
        "caseId": {
          "type": "number"
        },
        "authorizationId": {
          "type": "number"
        },
        "authorizationNumber": {
          "type": "string"
        },
        "authorizationType": {
          "$ref": "#/definitions/type_3"
        },
        "authorizationCategory": {
          "$ref": "#/definitions/type_3"
        },
        "facility": {
          "type": "string"
        },
        "comments": {
          "type": "string"
        },
        "authorizationStatus": {
          "$ref": "#/definitions/type_3"
        },
        "memberEligibility": {
          "type": "string"
        },
        "diagnosisCodes": {
          "type": "array",
          "items": {
            "$ref": "#/definitions/items"
          }
        },
        "procedureCodes": {
          "type": "array",
          "items": {
            "$ref": "#/definitions/items_4"
          }
        },
        "effectiveFromDate": {
          "type": "string"
        },
        "effectiveToDate": {
          "type": "string"
        },
        "authorizationMember": {
          "$ref": "#/definitions/type_2"
        },
        "class": {
          "type": "string"
        },
        "receiveDate": {
          "type": "string"
        },
        "statusChangeDate": {
          "type": "string"
        },
        "approveDenyDate": {
          "type": "string"
        },
        "createdDateTime": {
          "type": "string"
        },
        "modifiedDateTime": {
          "type": "string"
        }
      }
    },
    "caseAuthorizationUpdate": {
      "example": {
        "uuid": "a25f5974-e7df-43be-b048-23f55e29c971",
        "comment": "",
        "status": "Pending"
      },
      "type": "object",
      "additionalProperties": true,
      "required": [
        "uuid",
        "comment",
        "status"
      ],
      "properties": {
        "uuid": {
          "type": "string"
        },
        "comment": {
          "type": "string"
        },
        "status": {
          "type": "string"
        }
      }
    },
    "caseDocument": {
      "type": "object",
      "additionalProperties": true,
      "required": [
        "caseId",
        "documentId"
      ],
      "properties": {
        "caseId": {
          "type": "number"
        },
        "documentId": {
          "type": "number"
        },
        "documentType": {
          "$ref": "#/definitions/type_3"
        },
        "name": {
          "type": "string"
        },
        "fileType": {
          "type": "string"
        },
        "createdDateTime": {
          "type": "string"
        },
        "modifiedDateTime": {
          "type": "string"
        }
      }
    },
    "type_2": {
      "type": "object",
      "additionalProperties": true,
      "properties": {
        "type": {
          "type": "string"
        },
        "memberId": {
          "type": "number"
        },
        "memberFirstName": {
          "type": "string"
        },
        "memberLastName": {
          "type": "string"
        },
        "memberDOB": {
          "type": "string"
        }
      }
    },
    "type_3": {
      "type": "object",
      "additionalProperties": true,
      "properties": {
        "type": {
          "type": "string"
        },
        "id": {
          "type": "number"
        },
        "key": {
          "type": "string"
        },
        "description": {
          "type": "string"
        }
      }
    },
    "items": {
      "type": "object",
      "additionalProperties": true,
      "properties": {
        "code": {
          "type": "string"
        },
        "description": {
          "type": "string"
        },
        "primaryFlag": {
          "type": "boolean"
        }
      }
    },
    "items_4": {
      "type": "object",
      "additionalProperties": true,
      "properties": {
        "type": {
          "type": "string"
        },
        "code": {
          "type": "string"
        },
        "description": {
          "type": "string"
        }
      }
    }
  }
}